exoclasma_fastq/__init__.py
exoclasma_fastq/exoclasma_fastq.py
exoclasma_fastq-0.9.0.dist-info/METADATA
exoclasma_fastq-0.9.0.dist-info/WHEEL
exoclasma_fastq-0.9.0.dist-info/entry_points.txt
exoclasma_fastq-0.9.0.dist-info/licenses/LICENSE
exoclasma_fastq-0.9.0.dist-info/RECORD
