Metadata-Version: 2.1
Name: exoclasma-fastq
Version: 0.9.0
Summary: Different file formats to FastQ, part of ExoClasma Suite
Project-URL: Homepage, https://github.com/regnveig/exoclasma-fastq
Project-URL: Bug Tracker, https://github.com/regnveig/exoclasma-fastq/issues
Author-email: Emil Viesná <regnveig@yandex.ru>, Minja Fishman <minja-f@yandex.ru>
License-File: LICENSE
Keywords: bioinformatics,conversion,fastq,juicer,sra
Classifier: Development Status :: 3 - Alpha
Classifier: Environment :: Console
Classifier: Intended Audience :: Science/Research
Classifier: License :: OSI Approved :: GNU General Public License v3 (GPLv3)
Classifier: Natural Language :: English
Classifier: Operating System :: POSIX :: Linux
Classifier: Programming Language :: Python :: 3.10
Classifier: Topic :: Scientific/Engineering :: Bio-Informatics
Requires-Python: >=3.10
Requires-Dist: biopython
